HW2/sort.v
module sort#(parameter NUM_VALS = 8, WIDTH = 4)
    (input [NUM_VALS*WIDTH-1:0] A, output [NUM_VALS*WIDTH-1:0] B);
    integer i;
    integer j;
    reg [WIDTH-1:0] tmp [NUM_VALS];
    
    always@ * begin
        // store input in a reg
        for(i = 0; i < NUM_VALS; i+=1) begin
            tmp[NUM_VALS-1-i] = A[((i+1)*WIDTH-1) -: WIDTH];
        end
        
        // sort the reg
        for(i = 0; i < NUM_VALS; i+=1) begin
            #1; // delay for stimulation
            for(j = 1; j < NUM_VALS-i; j+=1) begin
                {tmp[j-1], tmp[j]} = tmp[j-1] > tmp[j] ? {tmp[j-1], tmp[j]} : {tmp[j], tmp[j-1]};
            end
        end
        
    end

    generate
        genvar k;
        for(k = 0; k < NUM_VALS; k+=1) begin
            assign B[((k+1)*WIDTH-1) -: WIDTH] = tmp[NUM_VALS-1-k];
        end    
    endgenerate

endmodule

HW2/sort_tb.v
module sort_tb #(parameter NUM_VALS = 8, WIDTH = 4);
    reg [NUM_VALS*WIDTH-1:0] in;
    wire [NUM_VALS*WIDTH-1:0] out;
    integer i;
    sort #(.NUM_VALS(8), .WIDTH(4)) dut(.A(in), .B(out));
    initial begin
    // Setup the signal dump file.
    $dumpfile("waveform.vcd"); // Set the name of the dump file.
    $dumpvars; // Save all signals to the dump file.
    in = $urandom; // for Verilog $urandom always returns 32-bit
    #(NUM_VALS*NUM_VALS); // Delay time depends on the delay of sort()
    $write("In: ");
    for (i=0; i<NUM_VALS; i=i+1) $write("%0d ", in[32-i*WIDTH-1 -: 4]);$write("\nOut: ");
    for (i=0; i<NUM_VALS; i=i+1) $write("%0d ", out[32-i*WIDTH-1 -: 4]);$write("\n");
    $finish;
    end
endmodule

HW2/waveform.vcd
$version Generated by VerilatedVcd $end
$timescale 1ps $end
 $scope module $rootio $end
 $upscope $end
 $scope module sort_tb $end
  $var wire 32 0 NUM_VALS [31:0] $end
  $var wire 32 1 WIDTH [31:0] $end
  $var wire 32 . in [31:0] $end
  $var wire 32 # out [31:0] $end
  $var wire 32 / i [31:0] $end
  $scope module dut $end
   $var wire 32 0 NUM_VALS [31:0] $end
   $var wire 32 1 WIDTH [31:0] $end
   $var wire 32 . A [31:0] $end
   $var wire 32 # B [31:0] $end
   $var wire 32 $ i [31:0] $end
   $var wire 32 % j [31:0] $end
   $var wire 4 & tmp[0] [3:0] $end
   $var wire 4 ' tmp[1] [3:0] $end
   $var wire 4 ( tmp[2] [3:0] $end
   $var wire 4 ) tmp[3] [3:0] $end
   $var wire 4 * tmp[4] [3:0] $end
   $var wire 4 + tmp[5] [3:0] $end
   $var wire 4 , tmp[6] [3:0] $end
   $var wire 4 - tmp[7] [3:0] $end
  $upscope $end
 $upscope $end
$enddefinitions $end


#0
b01111001011101100111001111000100 #
b00000000000000000000000000001000 $
b00000000000000000000000000000000 %
b0111 &
b1001 '
b0111 (
b0110 )
b0111 *
b0011 +
b1100 ,
b0100 -
b01111001011101100111001111000100 .
b00000000000000000000000000000000 /
b00000000000000000000000000001000 0
b00000000000000000000000000000100 1
#1
b10010111011101110110110001000011 #
b00000000000000000000000000000001 $
b00000000000000000000000000001000 %
b1001 &
b0111 '
b0111 )
b0110 *
b1100 +
b0100 ,
b0011 -
#2
b10010111011101111100011001000011 #
b00000000000000000000000000000010 $
b00000000000000000000000000000111 %
b1100 *
b0110 +
#3
b10010111011111000111011001000011 #
b00000000000000000000000000000011 $
b00000000000000000000000000000110 %
b1100 )
b0111 *
#4
b10010111110001110111011001000011 #
b00000000000000000000000000000100 $
b00000000000000000000000000000101 %
b1100 (
b0111 )
#5
b10011100011101110111011001000011 #
b00000000000000000000000000000101 $
b00000000000000000000000000000100 %
b1100 '
b0111 (
#6
b11001001011101110111011001000011 #
b00000000000000000000000000000110 $
b00000000000000000000000000000011 %
b1100 &
b1001 '
#7
b00000000000000000000000000000111 $
b00000000000000000000000000000010 %
#8
b01111001011101100111001111000100 #
b00000000000000000000000000001000 $
b00000000000000000000000000000001 %
b0111 &
b0110 )
b0011 +
b1100 ,
b0100 -
#9
b10010111011101110110110001000011 #
b00000000000000000000000000000001 $
b00000000000000000000000000001000 %
b1001 &
b0111 '
b0111 )
b0110 *
b1100 +
b0100 ,
b0011 -
#10
b10010111011101111100011001000011 #
b00000000000000000000000000000010 $
b00000000000000000000000000000111 %
b1100 *
b0110 +
#11
b10010111011111000111011001000011 #
b00000000000000000000000000000011 $
b00000000000000000000000000000110 %
b1100 )
b0111 *
#12
b10010111110001110111011001000011 #
b00000000000000000000000000000100 $
b00000000000000000000000000000101 %
b1100 (
b0111 )
#13
b10011100011101110111011001000011 #
b00000000000000000000000000000101 $
b00000000000000000000000000000100 %
b1100 '
b0111 (
#14
b11001001011101110111011001000011 #
b00000000000000000000000000000110 $
b00000000000000000000000000000011 %
b1100 &
b1001 '
#15
b00000000000000000000000000000111 $
b00000000000000000000000000000010 %
#16
b01111001011101100111001111000100 #
b00000000000000000000000000001000 $
b00000000000000000000000000000001 %
b0111 &
b0110 )
b0011 +
b1100 ,
b0100 -
#17
b10010111011101110110110001000011 #
b00000000000000000000000000000001 $
b00000000000000000000000000001000 %
b1001 &
b0111 '
b0111 )
b0110 *
b1100 +
b0100 ,
b0011 -
#18
b10010111011101111100011001000011 #
b00000000000000000000000000000010 $
b00000000000000000000000000000111 %
b1100 *
b0110 +
#19
b10010111011111000111011001000011 #
b00000000000000000000000000000011 $
b00000000000000000000000000000110 %
b1100 )
b0111 *
#20
b10010111110001110111011001000011 #
b00000000000000000000000000000100 $
b00000000000000000000000000000101 %
b1100 (
b0111 )
#21
b10011100011101110111011001000011 #
b00000000000000000000000000000101 $
b00000000000000000000000000000100 %
b1100 '
b0111 (
#22
b11001001011101110111011001000011 #
b00000000000000000000000000000110 $
b00000000000000000000000000000011 %
b1100 &
b1001 '
#23
b00000000000000000000000000000111 $
b00000000000000000000000000000010 %
#24
b01111001011101100111001111000100 #
b00000000000000000000000000001000 $
b00000000000000000000000000000001 %
b0111 &
b0110 )
b0011 +
b1100 ,
b0100 -
#25
b10010111011101110110110001000011 #
b00000000000000000000000000000001 $
b00000000000000000000000000001000 %
b1001 &
b0111 '
b0111 )
b0110 *
b1100 +
b0100 ,
b0011 -
#26
b10010111011101111100011001000011 #
b00000000000000000000000000000010 $
b00000000000000000000000000000111 %
b1100 *
b0110 +
#27
b10010111011111000111011001000011 #
b00000000000000000000000000000011 $
b00000000000000000000000000000110 %
b1100 )
b0111 *
#28
b10010111110001110111011001000011 #
b00000000000000000000000000000100 $
b00000000000000000000000000000101 %
b1100 (
b0111 )
#29
b10011100011101110111011001000011 #
b00000000000000000000000000000101 $
b00000000000000000000000000000100 %
b1100 '
b0111 (
#30
b11001001011101110111011001000011 #
b00000000000000000000000000000110 $
b00000000000000000000000000000011 %
b1100 &
b1001 '
#31
b00000000000000000000000000000111 $
b00000000000000000000000000000010 %
#32
b01111001011101100111001111000100 #
b00000000000000000000000000001000 $
b00000000000000000000000000000001 %
b0111 &
b0110 )
b0011 +
b1100 ,
b0100 -
#33
b10010111011101110110110001000011 #
b00000000000000000000000000000001 $
b00000000000000000000000000001000 %
b1001 &
b0111 '
b0111 )
b0110 *
b1100 +
b0100 ,
b0011 -
#34
b10010111011101111100011001000011 #
b00000000000000000000000000000010 $
b00000000000000000000000000000111 %
b1100 *
b0110 +
#35
b10010111011111000111011001000011 #
b00000000000000000000000000000011 $
b00000000000000000000000000000110 %
b1100 )
b0111 *
#36
b10010111110001110111011001000011 #
b00000000000000000000000000000100 $
b00000000000000000000000000000101 %
b1100 (
b0111 )
#37
b10011100011101110111011001000011 #
b00000000000000000000000000000101 $
b00000000000000000000000000000100 %
b1100 '
b0111 (
#38
b11001001011101110111011001000011 #
b00000000000000000000000000000110 $
b00000000000000000000000000000011 %
b1100 &
b1001 '
#39
b00000000000000000000000000000111 $
b00000000000000000000000000000010 %
#40
b01111001011101100111001111000100 #
b00000000000000000000000000001000 $
b00000000000000000000000000000001 %
b0111 &
b0110 )
b0011 +
b1100 ,
b0100 -
#41
b10010111011101110110110001000011 #
b00000000000000000000000000000001 $
b00000000000000000000000000001000 %
b1001 &
b0111 '
b0111 )
b0110 *
b1100 +
b0100 ,
b0011 -
#42
b10010111011101111100011001000011 #
b00000000000000000000000000000010 $
b00000000000000000000000000000111 %
b1100 *
b0110 +
#43
b10010111011111000111011001000011 #
b00000000000000000000000000000011 $
b00000000000000000000000000000110 %
b1100 )
b0111 *
#44
b10010111110001110111011001000011 #
b00000000000000000000000000000100 $
b00000000000000000000000000000101 %
b1100 (
b0111 )
#45
b10011100011101110111011001000011 #
b00000000000000000000000000000101 $
b00000000000000000000000000000100 %
b1100 '
b0111 (
#46
b11001001011101110111011001000011 #
b00000000000000000000000000000110 $
b00000000000000000000000000000011 %
b1100 &
b1001 '
#47
b00000000000000000000000000000111 $
b00000000000000000000000000000010 %
#48
b01111001011101100111001111000100 #
b00000000000000000000000000001000 $
b00000000000000000000000000000001 %
b0111 &
b0110 )
b0011 +
b1100 ,
b0100 -
#49
b10010111011101110110110001000011 #
b00000000000000000000000000000001 $
b00000000000000000000000000001000 %
b1001 &
b0111 '
b0111 )
b0110 *
b1100 +
b0100 ,
b0011 -
#50
b10010111011101111100011001000011 #
b00000000000000000000000000000010 $
b00000000000000000000000000000111 %
b1100 *
b0110 +
#51
b10010111011111000111011001000011 #
b00000000000000000000000000000011 $
b00000000000000000000000000000110 %
b1100 )
b0111 *
#52
b10010111110001110111011001000011 #
b00000000000000000000000000000100 $
b00000000000000000000000000000101 %
b1100 (
b0111 )
#53
b10011100011101110111011001000011 #
b00000000000000000000000000000101 $
b00000000000000000000000000000100 %
b1100 '
b0111 (
#54
b11001001011101110111011001000011 #
b00000000000000000000000000000110 $
b00000000000000000000000000000011 %
b1100 &
b1001 '
#55
b00000000000000000000000000000111 $
b00000000000000000000000000000010 %
#56
b01111001011101100111001111000100 #
b00000000000000000000000000001000 $
b00000000000000000000000000000001 %
b0111 &
b0110 )
b0011 +
b1100 ,
b0100 -
#57
b10010111011101110110110001000011 #
b00000000000000000000000000000001 $
b00000000000000000000000000001000 %
b1001 &
b0111 '
b0111 )
b0110 *
b1100 +
b0100 ,
b0011 -
#58
b10010111011101111100011001000011 #
b00000000000000000000000000000010 $
b00000000000000000000000000000111 %
b1100 *
b0110 +
#59
b10010111011111000111011001000011 #
b00000000000000000000000000000011 $
b00000000000000000000000000000110 %
b1100 )
b0111 *
#60
b10010111110001110111011001000011 #
b00000000000000000000000000000100 $
b00000000000000000000000000000101 %
b1100 (
b0111 )
#61
b10011100011101110111011001000011 #
b00000000000000000000000000000101 $
b00000000000000000000000000000100 %
b1100 '
b0111 (
#62
b11001001011101110111011001000011 #
b00000000000000000000000000000110 $
b00000000000000000000000000000011 %
b1100 &
b1001 '
#63
b00000000000000000000000000000111 $
b00000000000000000000000000000010 %
#64
b01111001011101100111001111000100 #
b00000000000000000000000000001000 $
b00000000000000000000000000000001 %
b0111 &
b0110 )
b0011 +
b1100 ,
b0100 -
b00000000000000000000000000001000 /
